rfcnt/LICENSE
rfcnt/README.md
rfcnt/__init__.py
rfcnt/prebuilds.json
rfcnt/requirements.txt
rfcnt/rfcnt.cp39-win_amd64.pyd
rfcnt/rfcnt.pyi
rfcnt/run_examples.py
rfcnt/run_tests.py
rfcnt/setup.py
rfcnt/utils.py
rfcnt/version.py
rfcnt/_ext/rfcnt_npy_1_23_2_api_v16.cp39-win_amd64.pyd
rfcnt/_ext/rfcnt_npy_2_0_0_api_v18.cp311-win_amd64.pyd
rfcnt/_ext/rfcnt_npy_2_0_0_api_v18.cp39-win_amd64.pyd
rfcnt/tests/__init__.py
rfcnt/tests/examples.py
rfcnt/tests/long_series.csv
rfcnt/tests/test_rfcnt.py
rfcnt-0.5.0.dist-info/licenses/LICENSE
rfcnt-0.5.0.dist-info/METADATA
rfcnt-0.5.0.dist-info/WHEEL
rfcnt-0.5.0.dist-info/top_level.txt
rfcnt-0.5.0.dist-info/RECORD
