Metadata-Version: 2.4
Name: rfcnt
Version: 0.5.0
Summary: Python interface for rainflow counting
Home-page: http://github.com/a-ma72/rainflow
Author: Andreas Martin
License: BSD-2-Clause
Keywords: rainflow counting
Classifier: Development Status :: 6 - Mature
Classifier: Environment :: Console
Classifier: Framework :: Buildout :: Extension
Classifier: Intended Audience :: Developers
Classifier: Intended Audience :: Education
Classifier: Intended Audience :: Information Technology
Classifier: Intended Audience :: Science/Research
Classifier: License :: OSI Approved :: BSD License
Classifier: Natural Language :: English
Classifier: Operating System :: MacOS :: MacOS X
Classifier: Operating System :: Microsoft :: Windows
Classifier: Operating System :: POSIX
Classifier: Programming Language :: Python :: 3
Classifier: Programming Language :: C++
Classifier: Programming Language :: C
Classifier: Topic :: Scientific/Engineering
Classifier: Topic :: Scientific/Engineering :: Information Analysis
Classifier: Topic :: Scientific/Engineering :: Physics
License-File: LICENSE
Requires-Dist: numpy
Dynamic: author
Dynamic: classifier
Dynamic: description
Dynamic: description-content-type
Dynamic: home-page
Dynamic: keywords
Dynamic: license
Dynamic: license-file
Dynamic: requires-dist
Dynamic: summary
